asm_codes.vh
parameter OP_R = 6'b000000;
parameter OP_ADDI = 6'b001000;
parameter OP_BEQ = 6'b000100;
parameter OP_BNE = 6'b000101;
parameter OP_LW = 6'b100011;
parameter OP_SW = 6'b101011;

parameter OPR_NOP = 6'b000000;
parameter OPR_ADD = 6'b100000;
parameter OPR_SUB = 6'b100010;

parameter ALU_ADD = 8'd00;
parameter ALU_SUB = 8'd01;

parameter R00 = 5'd00;
parameter R01 = 5'd01;
parameter R02 = 5'd02;
parameter R03 = 5'd03;
parameter R04 = 5'd04;
parameter R05 = 5'd05;
parameter R06 = 5'd06;
parameter R07 = 5'd07;
parameter R08 = 5'd08;
parameter R09 = 5'd09;
parameter R10 = 5'd10;
parameter R11 = 5'd11;
parameter R12 = 5'd12;
parameter R13 = 5'd13;
parameter R14 = 5'd14;
parameter R15 = 5'd15;
parameter R16 = 5'd16;
parameter R17 = 5'd17;
parameter R18 = 5'd18;
parameter R19 = 5'd19;
parameter R20 = 5'd20;
parameter R21 = 5'd21;
parameter R22 = 5'd22;
parameter R23 = 5'd23;
parameter R24 = 5'd24;
parameter R25 = 5'd25;
parameter R26 = 5'd26;
parameter R27 = 5'd27;
parameter R28 = 5'd28;
parameter R29 = 5'd29;
parameter R30 = 5'd30;
parameter R31 = 5'd31;

ALU.v

module alu_module (
  input [31:0] int1,
  input [31:0] int2,
  input [5:0] opcode,
  output reg [31:0] out, // reg is bad idea
  output zero
  );
 
  `include "asm_codes.vh"
  
  always @(int1, int2, opcode)
  begin
  	case (opcode)
  	ALU_ADD: out <= int1 + int2;
  	ALU_SUB: out <= int1 - int2;
  	default: out <= 0;
  	endcase
  end

  assign zero = (out == 0);

endmodule

register.v

module register (
  input [31:0] in,
  output reg [31:0] out,
  input write,
  input clock
  );
  
  always @(negedge clock) // Чтение данных по фронту clock, запись - по спаду
  begin
    if (write) out <= in;
  end

endmodule

registers_array.v
module registers_array (
  input [4:0] rnum1,
  input [4:0] rnum2,
  input [4:0] wnum,
  input [31:0] wdata,
  output reg [31:0] rdata1,
  output reg [31:0] rdata2,
  input clock,
  input write,
  input reset
  );
  
  // Выходы регистров
  wire [31:0]register_out [31:0];
  
  // Регистры
  register r00 (.clock(clock), .write(write & (wnum == 5'd00) | reset), .in(reset ? 32'd0 : wdata), .out(register_out[5'd00]));
  register r01 (.clock(clock), .write(write & (wnum == 5'd01) | reset), .in(reset ? 32'd0 : wdata), .out(register_out[5'd01]));
  register r02 (.clock(clock), .write(write & (wnum == 5'd02) | reset), .in(reset ? 32'd0 : wdata), .out(register_out[5'd02]));
  register r03 (.clock(clock), .write(write & (wnum == 5'd03) | reset), .in(reset ? 32'd0 : wdata), .out(register_out[5'd03]));
  register r04 (.clock(clock), .write(write & (wnum == 5'd04) | reset), .in(reset ? 32'd0 : wdata), .out(register_out[5'd04]));
  register r05 (.clock(clock), .write(write & (wnum == 5'd05) | reset), .in(reset ? 32'd0 : wdata), .out(register_out[5'd05]));
  register r06 (.clock(clock), .write(write & (wnum == 5'd06) | reset), .in(reset ? 32'd0 : wdata), .out(register_out[5'd06]));
  register r07 (.clock(clock), .write(write & (wnum == 5'd07) | reset), .in(reset ? 32'd0 : wdata), .out(register_out[5'd07]));
  register r08 (.clock(clock), .write(write & (wnum == 5'd08) | reset), .in(reset ? 32'd0 : wdata), .out(register_out[5'd08]));
  register r09 (.clock(clock), .write(write & (wnum == 5'd09) | reset), .in(reset ? 32'd0 : wdata), .out(register_out[5'd09]));
  register r10 (.clock(clock), .write(write & (wnum == 5'd10) | reset), .in(reset ? 32'd0 : wdata), .out(register_out[5'd10]));
  register r11 (.clock(clock), .write(write & (wnum == 5'd11) | reset), .in(reset ? 32'd0 : wdata), .out(register_out[5'd11]));
  register r12 (.clock(clock), .write(write & (wnum == 5'd12) | reset), .in(reset ? 32'd0 : wdata), .out(register_out[5'd12]));
  register r13 (.clock(clock), .write(write & (wnum == 5'd13) | reset), .in(reset ? 32'd0 : wdata), .out(register_out[5'd13]));
  register r14 (.clock(clock), .write(write & (wnum == 5'd14) | reset), .in(reset ? 32'd0 : wdata), .out(register_out[5'd14]));
  register r15 (.clock(clock), .write(write & (wnum == 5'd15) | reset), .in(reset ? 32'd0 : wdata), .out(register_out[5'd15]));
  register r16 (.clock(clock), .write(write & (wnum == 5'd16) | reset), .in(reset ? 32'd0 : wdata), .out(register_out[5'd16]));
  register r17 (.clock(clock), .write(write & (wnum == 5'd17) | reset), .in(reset ? 32'd0 : wdata), .out(register_out[5'd17]));
  register r18 (.clock(clock), .write(write & (wnum == 5'd18) | reset), .in(reset ? 32'd0 : wdata), .out(register_out[5'd18]));
  register r19 (.clock(clock), .write(write & (wnum == 5'd19) | reset), .in(reset ? 32'd0 : wdata), .out(register_out[5'd19]));
  register r20 (.clock(clock), .write(write & (wnum == 5'd20) | reset), .in(reset ? 32'd0 : wdata), .out(register_out[5'd20]));
  register r21 (.clock(clock), .write(write & (wnum == 5'd21) | reset), .in(reset ? 32'd0 : wdata), .out(register_out[5'd21]));
  register r22 (.clock(clock), .write(write & (wnum == 5'd22) | reset), .in(reset ? 32'd0 : wdata), .out(register_out[5'd22]));
  register r23 (.clock(clock), .write(write & (wnum == 5'd23) | reset), .in(reset ? 32'd0 : wdata), .out(register_out[5'd23]));
  register r24 (.clock(clock), .write(write & (wnum == 5'd24) | reset), .in(reset ? 32'd0 : wdata), .out(register_out[5'd24]));
  register r25 (.clock(clock), .write(write & (wnum == 5'd25) | reset), .in(reset ? 32'd0 : wdata), .out(register_out[5'd25]));
  register r26 (.clock(clock), .write(write & (wnum == 5'd26) | reset), .in(reset ? 32'd0 : wdata), .out(register_out[5'd26]));
  register r27 (.clock(clock), .write(write & (wnum == 5'd27) | reset), .in(reset ? 32'd0 : wdata), .out(register_out[5'd27]));
  register r28 (.clock(clock), .write(write & (wnum == 5'd28) | reset), .in(reset ? 32'd0 : wdata), .out(register_out[5'd28]));
  register r29 (.clock(clock), .write(write & (wnum == 5'd29) | reset), .in(reset ? 32'd0 : wdata), .out(register_out[5'd29]));
  register r30 (.clock(clock), .write(write & (wnum == 5'd30) | reset), .in(reset ? 32'd0 : wdata), .out(register_out[5'd30]));
  register r31 (.clock(clock), .write(write & (wnum == 5'd31) | reset), .in(reset ? 32'd0 : wdata), .out(register_out[5'd31]));
  
  // Мультиплексор, осуществляющий чтение rdata1 по фронту clock
  always @(posedge clock)
  begin
    case (rnum1)
    5'd00 : rdata1 <= register_out[00];
    5'd01 : rdata1 <= register_out[01];
    5'd02 : rdata1 <= register_out[02];
    5'd03 : rdata1 <= register_out[03];
    5'd04 : rdata1 <= register_out[04];
    5'd05 : rdata1 <= register_out[05];
    5'd06 : rdata1 <= register_out[06];
    5'd07 : rdata1 <= register_out[07];
    5'd08 : rdata1 <= register_out[08];
    5'd09 : rdata1 <= register_out[09];
    5'd10 : rdata1 <= register_out[10];
    5'd11 : rdata1 <= register_out[11];
    5'd12 : rdata1 <= register_out[12];
    5'd13 : rdata1 <= register_out[13];
    5'd14 : rdata1 <= register_out[14];
    5'd15 : rdata1 <= register_out[15];
    5'd16 : rdata1 <= register_out[16];
    5'd17 : rdata1 <= register_out[17];
    5'd18 : rdata1 <= register_out[18];
    5'd19 : rdata1 <= register_out[19];
    5'd20 : rdata1 <= register_out[20];
    5'd21 : rdata1 <= register_out[21];
    5'd22 : rdata1 <= register_out[22];
    5'd23 : rdata1 <= register_out[23];
    5'd24 : rdata1 <= register_out[24];
    5'd25 : rdata1 <= register_out[25];
    5'd26 : rdata1 <= register_out[26];
    5'd27 : rdata1 <= register_out[27];
    5'd28 : rdata1 <= register_out[28];
    5'd29 : rdata1 <= register_out[29];
    5'd30 : rdata1 <= register_out[30];
    5'd31 : rdata1 <= register_out[31];
    default: rdata1 <= 0;
    endcase
  end
  
  // Мультиплексор, осуществляющий чтение rdata2 по фронту clock
  always @(posedge clock)
  begin
    case (rnum2)
    5'd00 : rdata2 <= register_out[00];
    5'd01 : rdata2 <= register_out[01];
    5'd02 : rdata2 <= register_out[02];
    5'd03 : rdata2 <= register_out[03];
    5'd04 : rdata2 <= register_out[04];
    5'd05 : rdata2 <= register_out[05];
    5'd06 : rdata2 <= register_out[06];
    5'd07 : rdata2 <= register_out[07];
    5'd08 : rdata2 <= register_out[08];
    5'd09 : rdata2 <= register_out[09];
    5'd10 : rdata2 <= register_out[10];
    5'd11 : rdata2 <= register_out[11];
    5'd12 : rdata2 <= register_out[12];
    5'd13 : rdata2 <= register_out[13];
    5'd14 : rdata2 <= register_out[14];
    5'd15 : rdata2 <= register_out[15];
    5'd16 : rdata2 <= register_out[16];
    5'd17 : rdata2 <= register_out[17];
    5'd18 : rdata2 <= register_out[18];
    5'd19 : rdata2 <= register_out[19];
    5'd20 : rdata2 <= register_out[20];
    5'd21 : rdata2 <= register_out[21];
    5'd22 : rdata2 <= register_out[22];
    5'd23 : rdata2 <= register_out[23];
    5'd24 : rdata2 <= register_out[24];
    5'd25 : rdata2 <= register_out[25];
    5'd26 : rdata2 <= register_out[26];
    5'd27 : rdata2 <= register_out[27];
    5'd28 : rdata2 <= register_out[28];
    5'd29 : rdata2 <= register_out[29];
    5'd30 : rdata2 <= register_out[30];
    5'd31 : rdata2 <= register_out[31];
    default: rdata2 <= 0;
    endcase
  end
  
endmodule

CPU.v

module cpu_module (
  input [31:0] instr_in,
  output [31:0] instr_sel,
  input clock,
  input reset
  );

  `include "asm_codes.vh"

  // Разбор инструкции
  wire [5:0] instr_opcode = instr_in[31:26]; // 6 бит
  // Инструкции P-типа
  wire [4:0] instr_rs = instr_in[25:21]; // 5 бит
  wire [4:0] instr_rt = instr_in[20:16]; // 5 бит
  wire [4:0] instr_rd = instr_in[15:11]; // 5 бит
  wire [4:0] instr_shamt = instr_in[10:6]; // 5 бит
  wire [5:0] instr_funct = instr_in[5:0]; // 6 бит
  // Инструкции L-типа
  wire [15:0] instr_imm = instr_in[15:0]; // 16 бит
  // Инструкции J-типа
  wire [25:0] instr_addr = instr_in[25:0]; // 26 бит

  // Счетчик команд
  wire [31:0]pc_out;
  wire [31:0]pc_in;
  wire pc_write;
  register pc (.clock(clock), .write(pc_write), .in(pc_in), .out(pc_out));

  assign instr_sel = pc_out; // Порядок имеет значение!
  assign pc_in = reset ? 32'd0 : (pc_out + 32'd4); // Пока PC=PC+4;
  assign pc_write = 1'b1;
  
  // Регистры процессора
  wire [4:0]regs_rnum1;
  wire [4:0]regs_rnum2;
  wire [4:0]regs_wnum;
  wire [31:0]regs_rdata1;
  wire [31:0]regs_rdata2;
  wire [31:0]regs_wdata;
  wire regs_write;
  registers_array regs (.clock(clock), .write(regs_write), .rnum1(regs_rnum1), .rnum2(regs_rnum2), .wnum(regs_wnum), .rdata1(regs_rdata1), .rdata2(regs_rdata2), .wdata(regs_wdata), .reset(reset));

  assign regs_rnum1 = // Номер регистра А для чтения из блока регистров
    ((instr_opcode == OP_R) & (instr_funct == OPR_ADD)) ? instr_rs : // ADD: Первый аргумент аргумент инструкции
    (instr_opcode == OP_ADDI) ? instr_rt // ADDI: Второй аргумент инструкции
    : 5'b0;

  assign regs_rnum2 = // Номер регистра Б для чтения из блока регистров
    ((instr_opcode == OP_R) & (instr_funct == OPR_ADD)) ? instr_rd : // ADD: Второй аргумент аргумент инструкции
    (instr_opcode == OP_ADDI) ? 5'b0 // ADDI: Регистр Б не используется
    : 5'b0;

  assign regs_write = ( // При исполнении каких инструкции производить запись в регистры
    (instr_opcode == OP_R) & (instr_funct == OPR_ADD) | // ADD
    (instr_opcode == OP_ADDI) // ADDI
    ) ? 1'b1 : 1'b0;

  assign regs_wnum = // Номер регистра в который производить запись
    ((instr_opcode == OP_R) & (instr_funct == OPR_ADD)) ? instr_rd : // ADD: Третий аргумент инструкции
    (instr_opcode == OP_ADDI) ? instr_rs // ADDI: Первый аргумент инструкции
    : 32'b0;

  assign regs_wdata = // Данные для записи в блок регистров
    ((instr_opcode == OP_R) & (instr_funct == OPR_ADD)) ? alu_out : // ADD: С выхода АЛУ
    (instr_opcode == OP_ADDI) ? alu_out // ADDI: С выхода АЛУ
    : 32'b0;

  // АЛУ
  wire [31:0]alu_int1;
  wire [31:0]alu_int2;
  wire [5:0]alu_opcode;
  wire [31:0]alu_out;
  alu_module alu (.int1(alu_int1), .int2(alu_int2), .opcode(alu_opcode), .out(alu_out));

  assign alu_int1 = // Первый аргумент для АЛУ
    ((instr_opcode == OP_R) & (instr_funct == OPR_ADD)) ? regs_rdata1 : // ADD: Регистр А из блока регистров
    (instr_opcode == OP_ADDI) ? regs_rdata1 // ADDI: Регистр А из блока регистров
    : 32'b0;

  assign alu_int2 = // Второй аргумент для АЛУ
    ((instr_opcode == OP_R) & (instr_funct == OPR_ADD)) ? regs_rdata2 : // ADD: Регистр Б из блока регистров
    (instr_opcode == OP_ADDI) ? instr_imm // ADDI: Константа из инструкции
    : 32'b0;

  assign alu_opcode = // Операция для АЛУ
    ((instr_opcode == OP_R) & (instr_funct == OPR_ADD)) ? ALU_ADD : // ADD: Сложить
    (instr_opcode == OP_ADDI) ? ALU_ADD // ADDI: Сложить
    : 32'b0;

endmodule

instruction_memory.v
module instruction_memory (
  input [31:0] sel,
  output reg [31:0] out,
  input clock
  );
  
  `include "asm_codes.vh"
  
  always @(posedge clock)
  begin
    case (sel)
      32'h00000000 : out <= {OP_ADDI, R01, R01, 16'd1};       // ADDI R0, R0, 1
      32'h00000004 : out <= {OP_ADDI, R02, R02, 16'd2};       // ADDI R1, R1, 2
      32'h00000008 : out <= {OP_R, R01, R02, R03, OPR_ADD};   // ADD R0, R1, R2
      default: out <= 0;
    endcase
  end
endmodule

Testbench.v
`timescale 1ns/1ps

module mips_testbench();
// Входы делаем регистрами, а выходы - проводами
reg clock;
reg reset;
reg shutdown;

// Инициализируем переменные
initial begin
  $dumpfile("out.vcd");
  $dumpvars(0, mips_testbench);
  clock = 0;       // Начальное значнеие для clock
  reset = 0;       // Начальное значнеие для reset
  // Тактирование
  #1 reset = 1;    // Установка сброса
  #4 reset = 0;   // Снятие сброса
  #496 reset = 1;    // Установка сброса
  #500 shutdown = 1;    // Завершение

end

// Тактовый генератор
always begin
  #2 clock = ~clock;
end

// Конец симуляции
always @(posedge shutdown) begin
  $finish;
end

// Присоединяем модули
wire [31:0]mem_sel;
wire [31:0]mem_out;

instruction_memory mem (.sel(mem_sel), .out(mem_out), .clock(clock));
cpu_module cpu (.instr_in(mem_out), .instr_sel(mem_sel), .clock(clock), .reset(reset));

endmodule

out.vcd
$date
	Thu Feb 02 02:13:31 2017
$end
$version
	Icarus Verilog
$end
$timescale
	1ps
$end
$scope module mips_testbench $end
$var wire 32 ! mem_sel [31:0] $end
$var wire 32 " mem_out [31:0] $end
$var reg 1 # clock $end
$var reg 1 $ reset $end
$var reg 1 % shutdown $end
$scope module cpu $end
$var wire 1 # clock $end
$var wire 32 & instr_sel [31:0] $end
$var wire 1 ' pc_write $end
$var wire 1 $ reset $end
$var wire 1 ( regs_write $end
$var wire 5 ) regs_wnum [4:0] $end
$var wire 32 * regs_wdata [31:0] $end
$var wire 5 + regs_rnum2 [4:0] $end
$var wire 5 , regs_rnum1 [4:0] $end
$var wire 32 - regs_rdata2 [31:0] $end
$var wire 32 . regs_rdata1 [31:0] $end
$var wire 32 / pc_out [31:0] $end
$var wire 32 0 pc_in [31:0] $end
$var wire 5 1 instr_shamt [4:0] $end
$var wire 5 2 instr_rt [4:0] $end
$var wire 5 3 instr_rs [4:0] $end
$var wire 5 4 instr_rd [4:0] $end
$var wire 6 5 instr_opcode [5:0] $end
$var wire 32 6 instr_in [31:0] $end
$var wire 16 7 instr_imm [15:0] $end
$var wire 6 8 instr_funct [5:0] $end
$var wire 26 9 instr_addr [25:0] $end
$var wire 32 : alu_out [31:0] $end
$var wire 6 ; alu_opcode [5:0] $end
$var wire 32 < alu_int2 [31:0] $end
$var wire 32 = alu_int1 [31:0] $end
$scope module alu $end
$var wire 32 > int1 [31:0] $end
$var wire 32 ? int2 [31:0] $end
$var wire 6 @ opcode [5:0] $end
$var wire 1 A zero $end
$var reg 32 B out [31:0] $end
$upscope $end
$scope module pc $end
$var wire 1 # clock $end
$var wire 32 C in [31:0] $end
$var wire 1 ' write $end
$var reg 32 D out [31:0] $end
$upscope $end
$scope module regs $end
$var wire 1 # clock $end
$var wire 1 $ reset $end
$var wire 5 E rnum1 [4:0] $end
$var wire 5 F rnum2 [4:0] $end
$var wire 32 G wdata [31:0] $end
$var wire 5 H wnum [4:0] $end
$var wire 1 ( write $end
$var reg 32 I rdata1 [31:0] $end
$var reg 32 J rdata2 [31:0] $end
$scope module r00 $end
$var wire 1 # clock $end
$var wire 32 K in [31:0] $end
$var wire 1 L write $end
$var reg 32 M out [31:0] $end
$upscope $end
$scope module r01 $end
$var wire 1 # clock $end
$var wire 32 N in [31:0] $end
$var wire 1 O write $end
$var reg 32 P out [31:0] $end
$upscope $end
$scope module r02 $end
$var wire 1 # clock $end
$var wire 32 Q in [31:0] $end
$var wire 1 R write $end
$var reg 32 S out [31:0] $end
$upscope $end
$scope module r03 $end
$var wire 1 # clock $end
$var wire 32 T in [31:0] $end
$var wire 1 U write $end
$var reg 32 V out [31:0] $end
$upscope $end
$scope module r04 $end
$var wire 1 # clock $end
$var wire 32 W in [31:0] $end
$var wire 1 X write $end
$var reg 32 Y out [31:0] $end
$upscope $end
$scope module r05 $end
$var wire 1 # clock $end
$var wire 32 Z in [31:0] $end
$var wire 1 [ write $end
$var reg 32 \ out [31:0] $end
$upscope $end
$scope module r06 $end
$var wire 1 # clock $end
$var wire 32 ] in [31:0] $end
$var wire 1 ^ write $end
$var reg 32 _ out [31:0] $end
$upscope $end
$scope module r07 $end
$var wire 1 # clock $end
$var wire 32 ` in [31:0] $end
$var wire 1 a write $end
$var reg 32 b out [31:0] $end
$upscope $end
$scope module r08 $end
$var wire 1 # clock $end
$var wire 32 c in [31:0] $end
$var wire 1 d write $end
$var reg 32 e out [31:0] $end
$upscope $end
$scope module r09 $end
$var wire 1 # clock $end
$var wire 32 f in [31:0] $end
$var wire 1 g write $end
$var reg 32 h out [31:0] $end
$upscope $end
$scope module r10 $end
$var wire 1 # clock $end
$var wire 32 i in [31:0] $end
$var wire 1 j write $end
$var reg 32 k out [31:0] $end
$upscope $end
$scope module r11 $end
$var wire 1 # clock $end
$var wire 32 l in [31:0] $end
$var wire 1 m write $end
$var reg 32 n out [31:0] $end
$upscope $end
$scope module r12 $end
$var wire 1 # clock $end
$var wire 32 o in [31:0] $end
$var wire 1 p write $end
$var reg 32 q out [31:0] $end
$upscope $end
$scope module r13 $end
$var wire 1 # clock $end
$var wire 32 r in [31:0] $end
$var wire 1 s write $end
$var reg 32 t out [31:0] $end
$upscope $end
$scope module r14 $end
$var wire 1 # clock $end
$var wire 32 u in [31:0] $end
$var wire 1 v write $end
$var reg 32 w out [31:0] $end
$upscope $end
$scope module r15 $end
$var wire 1 # clock $end
$var wire 32 x in [31:0] $end
$var wire 1 y write $end
$var reg 32 z out [31:0] $end
$upscope $end
$scope module r16 $end
$var wire 1 # clock $end
$var wire 32 { in [31:0] $end
$var wire 1 | write $end
$var reg 32 } out [31:0] $end
$upscope $end
$scope module r17 $end
$var wire 1 # clock $end
$var wire 32 ~ in [31:0] $end
$var wire 1 !" write $end
$var reg 32 "" out [31:0] $end
$upscope $end
$scope module r18 $end
$var wire 1 # clock $end
$var wire 32 #" in [31:0] $end
$var wire 1 $" write $end
$var reg 32 %" out [31:0] $end
$upscope $end
$scope module r19 $end
$var wire 1 # clock $end
$var wire 32 &" in [31:0] $end
$var wire 1 '" write $end
$var reg 32 (" out [31:0] $end
$upscope $end
$scope module r20 $end
$var wire 1 # clock $end
$var wire 32 )" in [31:0] $end
$var wire 1 *" write $end
$var reg 32 +" out [31:0] $end
$upscope $end
$scope module r21 $end
$var wire 1 # clock $end
$var wire 32 ," in [31:0] $end
$var wire 1 -" write $end
$var reg 32 ." out [31:0] $end
$upscope $end
$scope module r22 $end
$var wire 1 # clock $end
$var wire 32 /" in [31:0] $end
$var wire 1 0" write $end
$var reg 32 1" out [31:0] $end
$upscope $end
$scope module r23 $end
$var wire 1 # clock $end
$var wire 32 2" in [31:0] $end
$var wire 1 3" write $end
$var reg 32 4" out [31:0] $end
$upscope $end
$scope module r24 $end
$var wire 1 # clock $end
$var wire 32 5" in [31:0] $end
$var wire 1 6" write $end
$var reg 32 7" out [31:0] $end
$upscope $end
$scope module r25 $end
$var wire 1 # clock $end
$var wire 32 8" in [31:0] $end
$var wire 1 9" write $end
$var reg 32 :" out [31:0] $end
$upscope $end
$scope module r26 $end
$var wire 1 # clock $end
$var wire 32 ;" in [31:0] $end
$var wire 1 <" write $end
$var reg 32 =" out [31:0] $end
$upscope $end
$scope module r27 $end
$var wire 1 # clock $end
$var wire 32 >" in [31:0] $end
$var wire 1 ?" write $end
$var reg 32 @" out [31:0] $end
$upscope $end
$scope module r28 $end
$var wire 1 # clock $end
$var wire 32 A" in [31:0] $end
$var wire 1 B" write $end
$var reg 32 C" out [31:0] $end
$upscope $end
$scope module r29 $end
$var wire 1 # clock $end
$var wire 32 D" in [31:0] $end
$var wire 1 E" write $end
$var reg 32 F" out [31:0] $end
$upscope $end
$scope module r30 $end
$var wire 1 # clock $end
$var wire 32 G" in [31:0] $end
$var wire 1 H" write $end
$var reg 32 I" out [31:0] $end
$upscope $end
$scope module r31 $end
$var wire 1 # clock $end
$var wire 32 J" in [31:0] $end
$var wire 1 K" write $end
$var reg 32 L" out [31:0] $end
$upscope $end
$upscope $end
$upscope $end
$scope module mem $end
$var wire 1 # clock $end
$var wire 32 M" sel [31:0] $end
$var reg 32 N" out [31:0] $end
$upscope $end
$upscope $end
$enddefinitions $end
#0
$dumpvars
bx N"
bx M"
bx L"
xK"
bx J"
bx I"
xH"
bx G"
bx F"
xE"
bx D"
bx C"
xB"
bx A"
bx @"
x?"
bx >"
bx ="
x<"
bx ;"
bx :"
x9"
bx 8"
bx 7"
x6"
bx 5"
bx 4"
x3"
bx 2"
bx 1"
x0"
bx /"
bx ."
x-"
bx ,"
bx +"
x*"
bx )"
bx ("
x'"
bx &"
bx %"
x$"
bx #"
bx ""
x!"
bx ~
bx }
x|
bx {
bx z
xy
bx x
bx w
xv
bx u
bx t
xs
bx r
bx q
xp
bx o
bx n
xm
bx l
bx k
xj
bx i
bx h
xg
bx f
bx e
xd
bx c
bx b
xa
bx `
bx _
x^
bx ]
bx \
x[
bx Z
bx Y
xX
bx W
bx V
xU
bx T
bx S
xR
bx Q
bx P
xO
bx N
bx M
xL
bx K
bx J
bx I
bx H
bx G
bx F
bx E
bx D
bx C
bx B
xA
b0 @
bx ?
bx >
bx =
bx <
b0 ;
bx :
bx 9
bx 8
bx 7
bx 6
bx 5
bx 4
bx 3
bx 2
bx 1
bx 0
bx /
bx .
bx -
bx ,
bx +
bx *
bx )
x(
1'
bx &
x%
0$
0#
bx "
bx !
$end
#1000
b0 0
b0 C
1L
1O
1R
1U
1X
1[
1^
1a
1d
1g
1j
1m
1p
1s
1v
1y
1|
1!"
1$"
1'"
1*"
1-"
10"
13"
16"
19"
1<"
1?"
1B"
1E"
1H"
1K"
b0 K
b0 N
b0 Q
b0 T
b0 W
b0 Z
b0 ]
b0 `
b0 c
b0 f
b0 i
b0 l
b0 o
b0 r
b0 u
b0 x
b0 {
b0 ~
b0 #"
b0 &"
b0 )"
b0 ,"
b0 /"
b0 2"
b0 5"
b0 8"
b0 ;"
b0 >"
b0 A"
b0 D"
b0 G"
b0 J"
1$
#2000
1A
b0 :
b0 B
0(
b0 )
b0 H
b0 *
b0 G
b0 +
b0 F
b0 ,
b0 E
b0 9
b0 7
b0 8
b0 1
b0 4
b0 2
b0 3
b0 5
b0 =
b0 >
b0 <
b0 ?
b0 "
b0 6
b0 N"
b0 .
b0 I
b0 -
b0 J
1#
#4000
b0 L"
b0 I"
b0 F"
b0 C"
b0 @"
b0 ="
b0 :"
b0 7"
b0 4"
b0 1"
b0 ."
b0 +"
b0 ("
b0 %"
b0 ""
b0 }
b0 z
b0 w
b0 t
b0 q
b0 n
b0 k
b0 h
b0 e
b0 b
b0 _
b0 \
b0 Y
b0 V
b0 S
b0 P
b0 M
b0 !
b0 &
b0 M"
b0 /
b0 D
0#
#5000
b100 0
b100 C
0L
0O
0R
0U
0X
0[
0^
0a
0d
0g
0j
0m
0p
0s
0v
0y
0|
0!"
0$"
0'"
0*"
0-"
00"
03"
06"
09"
0<"
0?"
0B"
0E"
0H"
0K"
0$
#6000
b1 K
b1 N
b1 Q
b1 T
b1 W
b1 Z
b1 ]
b1 `
b1 c
b1 f
b1 i
b1 l
b1 o
b1 r
b1 u
b1 x
b1 {
b1 ~
b1 #"
b1 &"
b1 )"
b1 ,"
b1 /"
b1 2"
b1 5"
b1 8"
b1 ;"
b1 >"
b1 A"
b1 D"
b1 G"
b1 J"
b1 *
b1 G
0A
b1 :
b1 B
1O
b1 )
b1 H
b1 ,
b1 E
1(
b1 <
b1 ?
b1000010000000000000001 9
b1 7
b1 8
b1 2
b1 3
b1000 5
b100000001000010000000000000001 "
b100000001000010000000000000001 6
b100000001000010000000000000001 N"
1#
#8000
b1000 0
b1000 C
b100 !
b100 &
b100 M"
b100 /
b100 D
b1 P
0#
#10000
b11 K
b11 N
b11 Q
b11 T
b11 W
b11 Z
b11 ]
b11 `
b11 c
b11 f
b11 i
b11 l
b11 o
b11 r
b11 u
b11 x
b11 {
b11 ~
b11 #"
b11 &"
b11 )"
b11 ,"
b11 /"
b11 2"
b11 5"
b11 8"
b11 ;"
b11 >"
b11 A"
b11 D"
b11 G"
b11 J"
b11 *
b11 G
b11 :
b11 B
0O
1R
b10 )
b10 H
b10 <
b10 ?
b10 ,
b10 E
b1 =
b1 >
b10000100000000000000010 9
b10 7
b10 8
b10 2
b10 3
b100000010000100000000000000010 "
b100000010000100000000000000010 6
b100000010000100000000000000010 N"
b1 .
b1 I
1#
#12000
b1100 0
b1100 C
b11 S
b1000 !
b1000 &
b1000 M"
b1000 /
b1000 D
0#
#14000
1R
b0 ,
b0 E
b10 +
b10 F
1(
b0 <
b0 ?
b11 =
b11 >
b10001000011100000 9
b1000011100000 7
b100000 8
b11 1
b10 4
b1 2
b0 3
b0 5
b11 .
b11 I
b10001000011100000 "
b10001000011100000 6
b10001000011100000 N"
1#
#16000
b10000 0
b10000 C
b1100 !
b1100 &
b1100 M"
b1100 /
b1100 D
0#
#18000
1A
b0 :
b0 B
0L
0R
0(
b0 K
b0 N
b0 Q
b0 T
b0 W
b0 Z
b0 ]
b0 `
b0 c
b0 f
b0 i
b0 l
b0 o
b0 r
b0 u
b0 x
b0 {
b0 ~
b0 #"
b0 &"
b0 )"
b0 ,"
b0 /"
b0 2"
b0 5"
b0 8"
b0 ;"
b0 >"
b0 A"
b0 D"
b0 G"
b0 J"
b0 *
b0 G
b0 )
b0 H
b0 +
b0 F
b0 9
b0 7
b0 8
b0 1
b0 4
b0 2
b0 =
b0 >
b0 <
b0 ?
b0 "
b0 6
b0 N"
b0 .
b0 I
b11 -
b11 J
1#
#20000
b10100 0
b10100 C
b10000 !
b10000 &
b10000 M"
b10000 /
b10000 D
0#
#22000
b0 -
b0 J
1#
#24000
b11000 0
b11000 C
b10100 !
b10100 &
b10100 M"
b10100 /
b10100 D
0#
#26000
1#
#28000
b11100 0
b11100 C
b11000 !
b11000 &
b11000 M"
b11000 /
b11000 D
0#
#30000
1#
#32000
b100000 0
b100000 C
b11100 !
b11100 &
b11100 M"
b11100 /
b11100 D
0#
#34000
1#
#36000
b100100 0
b100100 C
b100000 !
b100000 &
b100000 M"
b100000 /
b100000 D
0#
#38000
1#
#40000
b101000 0
b101000 C
b100100 !
b100100 &
b100100 M"
b100100 /
b100100 D
0#
#42000
1#
#44000
b101100 0
b101100 C
b101000 !
b101000 &
b101000 M"
b101000 /
b101000 D
0#
#46000
1#
#48000
b110000 0
b110000 C
b101100 !
b101100 &
b101100 M"
b101100 /
b101100 D
0#
#50000
1#
#52000
b110100 0
b110100 C
b110000 !
b110000 &
b110000 M"
b110000 /
b110000 D
0#
#54000
1#
#56000
b111000 0
b111000 C
b110100 !
b110100 &
b110100 M"
b110100 /
b110100 D
0#
#58000
1#
#60000
b111100 0
b111100 C
b111000 !
b111000 &
b111000 M"
b111000 /
b111000 D
0#
#62000
1#
#64000
b1000000 0
b1000000 C
b111100 !
b111100 &
b111100 M"
b111100 /
b111100 D
0#
#66000
1#
#68000
b1000100 0
b1000100 C
b1000000 !
b1000000 &
b1000000 M"
b1000000 /
b1000000 D
0#
#70000
1#
#72000
b1001000 0
b1001000 C
b1000100 !
b1000100 &
b1000100 M"
b1000100 /
b1000100 D
0#
#74000
1#
#76000
b1001100 0
b1001100 C
b1001000 !
b1001000 &
b1001000 M"
b1001000 /
b1001000 D
0#
#78000
1#
#80000
b1010000 0
b1010000 C
b1001100 !
b1001100 &
b1001100 M"
b1001100 /
b1001100 D
0#
#82000
1#
#84000
b1010100 0
b1010100 C
b1010000 !
b1010000 &
b1010000 M"
b1010000 /
b1010000 D
0#
#86000
1#
#88000
b1011000 0
b1011000 C
b1010100 !
b1010100 &
b1010100 M"
b1010100 /
b1010100 D
0#
#90000
1#
#92000
b1011100 0
b1011100 C
b1011000 !
b1011000 &
b1011000 M"
b1011000 /
b1011000 D
0#
#94000
1#
#96000
b1100000 0
b1100000 C
b1011100 !
b1011100 &
b1011100 M"
b1011100 /
b1011100 D
0#
#98000
1#
#100000
b1100100 0
b1100100 C
b1100000 !
b1100000 &
b1100000 M"
b1100000 /
b1100000 D
0#
#102000
1#
